{
  "_comment" : "Created with OWL2VOWL (version 0.3.5), http://vowl.visualdataweb.org",
  "header" : {
    "languages" : [ "undefined" ],
    "baseIris" : [ "http://www.w3.org/2000/01/rdf-schema", "http://www.w3.org/2001/XMLSchema", "https://example.org/partidos" ],
    "title" : {
      "undefined" : "Ontología Deportes"
    },
    "iri" : "https://example.org/partidos/",
    "version" : "1.0.0",
    "author" : [ "Santiago Pereira Olmeda, Mateo Fraguas Abal, Gonzalo Landeira Rodríguez" ],
    "description" : {
      "undefined" : "Ontología para la gestión de competiciones deportivas, incluyendo partidos, equipos, campos, grupos y jornadas."
    },
    "other" : {
      "license" : [ {
        "identifier" : "license",
        "language" : "undefined",
        "value" : "https://creativecommons.org/licenses/by/4.0/",
        "type" : "iri"
      } ],
      "creator" : [ {
        "identifier" : "creator",
        "language" : "undefined",
        "value" : "Santiago Pereira Olmeda, Mateo Fraguas Abal, Gonzalo Landeira Rodríguez",
        "type" : "label"
      } ],
      "createdWith" : [ {
        "identifier" : "createdWith",
        "language" : "undefined",
        "value" : "https://chowlk.linkeddata.es/",
        "type" : "iri"
      } ],
      "versionInfo" : [ {
        "identifier" : "versionInfo",
        "language" : "undefined",
        "value" : "1.0.0",
        "type" : "label"
      } ],
      "title" : [ {
        "identifier" : "title",
        "language" : "undefined",
        "value" : "Ontología Deportes",
        "type" : "label"
      } ]
    }
  },
  "namespace" : [ ],
  "class" : [ {
    "id" : "15",
    "type" : "owl:Class"
  }, {
    "id" : "8",
    "type" : "rdfs:Datatype"
  }, {
    "id" : "19",
    "type" : "owl:Class"
  }, {
    "id" : "2",
    "type" : "rdfs:Datatype"
  }, {
    "id" : "22",
    "type" : "owl:Class"
  }, {
    "id" : "4",
    "type" : "owl:Class"
  }, {
    "id" : "25",
    "type" : "rdfs:Datatype"
  }, {
    "id" : "7",
    "type" : "owl:Class"
  }, {
    "id" : "29",
    "type" : "rdfs:Datatype"
  }, {
    "id" : "30",
    "type" : "rdfs:Datatype"
  }, {
    "id" : "12",
    "type" : "owl:Class"
  }, {
    "id" : "31",
    "type" : "rdfs:Datatype"
  }, {
    "id" : "18",
    "type" : "rdfs:Datatype"
  }, {
    "id" : "34",
    "type" : "rdfs:Datatype"
  }, {
    "id" : "35",
    "type" : "rdfs:Datatype"
  }, {
    "id" : "36",
    "type" : "rdfs:Datatype"
  }, {
    "id" : "1",
    "type" : "owl:Class"
  }, {
    "id" : "5",
    "type" : "rdfs:Datatype"
  }, {
    "id" : "38",
    "type" : "rdfs:Datatype"
  }, {
    "id" : "13",
    "type" : "rdfs:Datatype"
  }, {
    "id" : "33",
    "type" : "rdfs:Datatype"
  }, {
    "id" : "41",
    "type" : "rdfs:Datatype"
  }, {
    "id" : "42",
    "type" : "rdfs:Datatype"
  }, {
    "id" : "16",
    "type" : "owl:Class"
  }, {
    "id" : "44",
    "type" : "rdfs:Datatype"
  }, {
    "id" : "24",
    "type" : "rdfs:Datatype"
  }, {
    "id" : "10",
    "type" : "rdfs:Datatype"
  }, {
    "id" : "21",
    "type" : "rdfs:Datatype"
  }, {
    "id" : "45",
    "type" : "rdfs:Datatype"
  }, {
    "id" : "49",
    "type" : "rdfs:Datatype"
  }, {
    "id" : "50",
    "type" : "rdfs:Datatype"
  } ],
  "classAttribute" : [ {
    "iri" : "https://example.org/partidos/Jornada",
    "baseIri" : "https://example.org/partidos",
    "instances" : 0,
    "label" : {
      "IRI-based" : "Jornada",
      "undefined" : "Jornada"
    },
    "comment" : {
      "undefined" : "Jornada de una competición, identificada por código y fecha."
    },
    "id" : "15"
  }, {
    "iri" : "http://www.w3.org/2001/XMLSchema#string",
    "baseIri" : "http://www.w3.org/2001/XMLSchema",
    "id" : "8",
    "label" : {
      "IRI-based" : "string"
    }
  }, {
    "iri" : "https://example.org/partidos/Equipo",
    "baseIri" : "https://example.org/partidos",
    "instances" : 0,
    "label" : {
      "IRI-based" : "Equipo",
      "undefined" : "Equipo"
    },
    "comment" : {
      "undefined" : "Equipo participante en la competición."
    },
    "id" : "19"
  }, {
    "iri" : "http://www.w3.org/2001/XMLSchema#string",
    "baseIri" : "http://www.w3.org/2001/XMLSchema",
    "id" : "2",
    "label" : {
      "IRI-based" : "string"
    }
  }, {
    "iri" : "https://example.org/partidos/Distrito",
    "baseIri" : "https://example.org/partidos",
    "instances" : 0,
    "label" : {
      "IRI-based" : "Distrito",
      "undefined" : "Distrito"
    },
    "comment" : {
      "undefined" : "Distrito o zona geográfica donde está ubicado un campo."
    },
    "id" : "22"
  }, {
    "iri" : "https://example.org/partidos/Campo",
    "baseIri" : "https://example.org/partidos",
    "instances" : 0,
    "label" : {
      "IRI-based" : "Campo",
      "undefined" : "Campo"
    },
    "comment" : {
      "undefined" : "Instalación deportiva donde se celebran los partidos."
    },
    "id" : "4"
  }, {
    "iri" : "http://www.w3.org/2001/XMLSchema#string",
    "baseIri" : "http://www.w3.org/2001/XMLSchema",
    "id" : "25",
    "label" : {
      "IRI-based" : "string"
    }
  }, {
    "iri" : "https://example.org/partidos/Competicion",
    "baseIri" : "https://example.org/partidos",
    "instances" : 0,
    "label" : {
      "IRI-based" : "Competicion",
      "undefined" : "Competicion"
    },
    "comment" : {
      "undefined" : "Competición deportiva organizada dentro de un deporte y temporada."
    },
    "id" : "7"
  }, {
    "iri" : "http://www.w3.org/2001/XMLSchema#anyURI",
    "baseIri" : "http://www.w3.org/2001/XMLSchema",
    "id" : "29",
    "label" : {
      "IRI-based" : "anyURI"
    }
  }, {
    "iri" : "http://www.w3.org/2001/XMLSchema#integer",
    "baseIri" : "http://www.w3.org/2001/XMLSchema",
    "id" : "30",
    "label" : {
      "IRI-based" : "integer"
    }
  }, {
    "iri" : "https://example.org/partidos/Deporte",
    "baseIri" : "https://example.org/partidos",
    "instances" : 0,
    "label" : {
      "IRI-based" : "Deporte",
      "undefined" : "Deporte"
    },
    "comment" : {
      "undefined" : "Representa un deporte (p. ej. fútbol, baloncesto)."
    },
    "id" : "12"
  }, {
    "iri" : "http://www.w3.org/2001/XMLSchema#anyURI",
    "baseIri" : "http://www.w3.org/2001/XMLSchema",
    "id" : "31",
    "label" : {
      "IRI-based" : "anyURI"
    }
  }, {
    "iri" : "http://www.w3.org/2001/XMLSchema#string",
    "baseIri" : "http://www.w3.org/2001/XMLSchema",
    "id" : "18",
    "label" : {
      "IRI-based" : "string"
    }
  }, {
    "iri" : "http://www.w3.org/2001/XMLSchema#string",
    "baseIri" : "http://www.w3.org/2001/XMLSchema",
    "id" : "34",
    "label" : {
      "IRI-based" : "string"
    }
  }, {
    "iri" : "http://www.w3.org/2001/XMLSchema#integer",
    "baseIri" : "http://www.w3.org/2001/XMLSchema",
    "id" : "35",
    "label" : {
      "IRI-based" : "integer"
    }
  }, {
    "iri" : "http://www.w3.org/2001/XMLSchema#boolean",
    "baseIri" : "http://www.w3.org/2001/XMLSchema",
    "id" : "36",
    "label" : {
      "IRI-based" : "boolean"
    }
  }, {
    "iri" : "https://example.org/partidos/Grupo",
    "baseIri" : "https://example.org/partidos",
    "instances" : 0,
    "label" : {
      "IRI-based" : "Grupo",
      "undefined" : "Grupo"
    },
    "comment" : {
      "undefined" : "Grupo o categoría dentro de una competición."
    },
    "id" : "1"
  }, {
    "iri" : "http://www.w3.org/2001/XMLSchema#string",
    "baseIri" : "http://www.w3.org/2001/XMLSchema",
    "id" : "5",
    "label" : {
      "IRI-based" : "string"
    }
  }, {
    "iri" : "http://www.w3.org/2001/XMLSchema#string",
    "baseIri" : "http://www.w3.org/2001/XMLSchema",
    "id" : "38",
    "label" : {
      "IRI-based" : "string"
    }
  }, {
    "iri" : "http://www.w3.org/2001/XMLSchema#string",
    "baseIri" : "http://www.w3.org/2001/XMLSchema",
    "id" : "13",
    "label" : {
      "IRI-based" : "string"
    }
  }, {
    "iri" : "http://www.w3.org/2001/XMLSchema#integer",
    "baseIri" : "http://www.w3.org/2001/XMLSchema",
    "id" : "33",
    "label" : {
      "IRI-based" : "integer"
    }
  }, {
    "iri" : "http://www.w3.org/2001/XMLSchema#integer",
    "baseIri" : "http://www.w3.org/2001/XMLSchema",
    "id" : "41",
    "label" : {
      "IRI-based" : "integer"
    }
  }, {
    "iri" : "http://www.w3.org/2001/XMLSchema#float",
    "baseIri" : "http://www.w3.org/2001/XMLSchema",
    "id" : "42",
    "label" : {
      "IRI-based" : "float"
    }
  }, {
    "iri" : "https://example.org/partidos/Partido",
    "baseIri" : "https://example.org/partidos",
    "instances" : 0,
    "label" : {
      "IRI-based" : "Partido",
      "undefined" : "Partido"
    },
    "comment" : {
      "undefined" : "Encuentro deportivo entre dos equipos en un campo y fecha determinados."
    },
    "id" : "16"
  }, {
    "iri" : "http://www.w3.org/2001/XMLSchema#float",
    "baseIri" : "http://www.w3.org/2001/XMLSchema",
    "id" : "44",
    "label" : {
      "IRI-based" : "float"
    }
  }, {
    "iri" : "http://www.w3.org/2001/XMLSchema#string",
    "baseIri" : "http://www.w3.org/2001/XMLSchema",
    "id" : "24",
    "label" : {
      "IRI-based" : "string"
    }
  }, {
    "iri" : "http://www.w3.org/2001/XMLSchema#string",
    "baseIri" : "http://www.w3.org/2001/XMLSchema",
    "id" : "10",
    "label" : {
      "IRI-based" : "string"
    }
  }, {
    "iri" : "http://www.w3.org/2001/XMLSchema#date",
    "baseIri" : "http://www.w3.org/2001/XMLSchema",
    "id" : "21",
    "label" : {
      "IRI-based" : "date"
    }
  }, {
    "iri" : "http://www.w3.org/2001/XMLSchema#time",
    "baseIri" : "http://www.w3.org/2001/XMLSchema",
    "id" : "45",
    "label" : {
      "IRI-based" : "time"
    }
  }, {
    "iri" : "http://www.w3.org/2001/XMLSchema#string",
    "baseIri" : "http://www.w3.org/2001/XMLSchema",
    "id" : "49",
    "label" : {
      "IRI-based" : "string"
    }
  }, {
    "iri" : "http://www.w3.org/2001/XMLSchema#integer",
    "baseIri" : "http://www.w3.org/2001/XMLSchema",
    "id" : "50",
    "label" : {
      "IRI-based" : "integer"
    }
  } ],
  "property" : [ {
    "id" : "0",
    "type" : "owl:datatypeProperty"
  }, {
    "id" : "3",
    "type" : "owl:datatypeProperty"
  }, {
    "id" : "6",
    "type" : "owl:datatypeProperty"
  }, {
    "id" : "9",
    "type" : "owl:datatypeProperty"
  }, {
    "id" : "11",
    "type" : "owl:datatypeProperty"
  }, {
    "id" : "14",
    "type" : "owl:objectProperty"
  }, {
    "id" : "17",
    "type" : "owl:datatypeProperty"
  }, {
    "id" : "20",
    "type" : "owl:datatypeProperty"
  }, {
    "id" : "23",
    "type" : "owl:datatypeProperty"
  }, {
    "id" : "26",
    "type" : "owl:datatypeProperty"
  }, {
    "id" : "27",
    "type" : "owl:objectProperty"
  }, {
    "id" : "28",
    "type" : "owl:objectProperty"
  }, {
    "id" : "32",
    "type" : "owl:datatypeProperty"
  }, {
    "id" : "37",
    "type" : "owl:objectProperty"
  }, {
    "id" : "39",
    "type" : "owl:datatypeProperty"
  }, {
    "id" : "40",
    "type" : "owl:objectProperty"
  }, {
    "id" : "43",
    "type" : "owl:objectProperty"
  }, {
    "id" : "46",
    "type" : "owl:objectProperty"
  }, {
    "id" : "47",
    "type" : "owl:datatypeProperty"
  }, {
    "id" : "48",
    "type" : "owl:datatypeProperty"
  }, {
    "id" : "51",
    "type" : "owl:datatypeProperty"
  }, {
    "id" : "52",
    "type" : "owl:datatypeProperty"
  }, {
    "id" : "53",
    "type" : "owl:datatypeProperty"
  }, {
    "id" : "54",
    "type" : "owl:datatypeProperty"
  }, {
    "id" : "55",
    "type" : "owl:datatypeProperty"
  }, {
    "id" : "56",
    "type" : "owl:datatypeProperty"
  }, {
    "id" : "57",
    "type" : "owl:datatypeProperty"
  }, {
    "id" : "58",
    "type" : "owl:objectProperty"
  }, {
    "id" : "59",
    "type" : "owl:datatypeProperty"
  }, {
    "id" : "60",
    "type" : "owl:datatypeProperty"
  }, {
    "id" : "61",
    "type" : "owl:datatypeProperty"
  } ],
  "propertyAttribute" : [ {
    "iri" : "https://example.org/partidos/sexo",
    "baseIri" : "https://example.org/partidos",
    "range" : "2",
    "label" : {
      "IRI-based" : "sexo",
      "undefined" : "sexo"
    },
    "domain" : "1",
    "comment" : {
      "undefined" : "Categoría de sexo del grupo (masculino, femenino, mixto)."
    },
    "attributes" : [ "datatype" ],
    "id" : "0"
  }, {
    "iri" : "https://example.org/partidos/nombreCampo",
    "baseIri" : "https://example.org/partidos",
    "range" : "5",
    "label" : {
      "IRI-based" : "nombreCampo",
      "undefined" : "nombre campo"
    },
    "domain" : "4",
    "comment" : {
      "undefined" : "Nombre de la instalación deportiva."
    },
    "attributes" : [ "datatype" ],
    "id" : "3"
  }, {
    "iri" : "https://example.org/partidos/sistemaCompeticion",
    "baseIri" : "https://example.org/partidos",
    "range" : "8",
    "label" : {
      "IRI-based" : "sistemaCompeticion",
      "undefined" : "sistema competicion"
    },
    "domain" : "7",
    "comment" : {
      "undefined" : "Sistema de competición (liga, copa, liguilla, etc.)."
    },
    "attributes" : [ "datatype" ],
    "id" : "6"
  }, {
    "iri" : "https://example.org/partidos/fase",
    "baseIri" : "https://example.org/partidos",
    "range" : "10",
    "label" : {
      "IRI-based" : "fase",
      "undefined" : "fase"
    },
    "domain" : "1",
    "comment" : {
      "undefined" : "Fase de la competición a la que pertenece el grupo."
    },
    "attributes" : [ "datatype" ],
    "id" : "9"
  }, {
    "iri" : "https://example.org/partidos/nombreDeporte",
    "baseIri" : "https://example.org/partidos",
    "range" : "13",
    "label" : {
      "IRI-based" : "nombreDeporte",
      "undefined" : "nombre deporte"
    },
    "domain" : "12",
    "comment" : {
      "undefined" : "Nombre del deporte."
    },
    "attributes" : [ "datatype" ],
    "id" : "11"
  }, {
    "iri" : "https://example.org/partidos/tienePartido",
    "baseIri" : "https://example.org/partidos",
    "range" : "16",
    "label" : {
      "IRI-based" : "tienePartido",
      "undefined" : "tiene partido"
    },
    "domain" : "15",
    "comment" : {
      "undefined" : "Relaciona una jornada con los partidos que la componen."
    },
    "attributes" : [ "object" ],
    "id" : "14"
  }, {
    "iri" : "https://example.org/partidos/nombreGrupo",
    "baseIri" : "https://example.org/partidos",
    "range" : "18",
    "label" : {
      "IRI-based" : "nombreGrupo",
      "undefined" : "nombre grupo"
    },
    "domain" : "1",
    "comment" : {
      "undefined" : "Nombre del grupo dentro de la competición."
    },
    "attributes" : [ "datatype" ],
    "id" : "17"
  }, {
    "iri" : "https://example.org/partidos/fecha",
    "baseIri" : "https://example.org/partidos",
    "range" : "21",
    "label" : {
      "IRI-based" : "fecha",
      "undefined" : "fecha"
    },
    "domain" : "15",
    "comment" : {
      "undefined" : "Fecha de celebración de la jornada."
    },
    "attributes" : [ "datatype" ],
    "id" : "20"
  }, {
    "iri" : "https://example.org/partidos/estado",
    "baseIri" : "https://example.org/partidos",
    "range" : "24",
    "label" : {
      "IRI-based" : "estado",
      "undefined" : "estado"
    },
    "domain" : "16",
    "comment" : {
      "undefined" : "Estado del partido (programado, jugado, suspendido, etc.)."
    },
    "attributes" : [ "datatype" ],
    "id" : "23"
  }, {
    "iri" : "https://example.org/partidos/temporada",
    "baseIri" : "https://example.org/partidos",
    "range" : "25",
    "label" : {
      "IRI-based" : "temporada",
      "undefined" : "temporada"
    },
    "domain" : "7",
    "comment" : {
      "undefined" : "Temporada en formato texto (p. ej. 2014/2015)."
    },
    "attributes" : [ "datatype" ],
    "id" : "26"
  }, {
    "iri" : "https://example.org/partidos/tieneEquipoLocal",
    "baseIri" : "https://example.org/partidos",
    "range" : "19",
    "label" : {
      "IRI-based" : "tieneEquipoLocal",
      "undefined" : "tiene equipo local"
    },
    "domain" : "16",
    "comment" : {
      "undefined" : "Equipo que juega como local en el partido."
    },
    "attributes" : [ "object" ],
    "id" : "27"
  }, {
    "iri" : "https://example.org/partidos/tieneEquipoVisitante",
    "baseIri" : "https://example.org/partidos",
    "range" : "19",
    "label" : {
      "IRI-based" : "tieneEquipoVisitante",
      "undefined" : "tiene equipo visitante"
    },
    "domain" : "16",
    "comment" : {
      "undefined" : "Equipo que juega como visitante en el partido."
    },
    "attributes" : [ "object" ],
    "id" : "28"
  }, {
    "iri" : "https://example.org/partidos/codigoEquipo",
    "baseIri" : "https://example.org/partidos",
    "range" : "33",
    "label" : {
      "IRI-based" : "codigoEquipo",
      "undefined" : "codigo equipo"
    },
    "domain" : "19",
    "comment" : {
      "undefined" : "Código numérico identificador del equipo."
    },
    "attributes" : [ "datatype" ],
    "id" : "32"
  }, {
    "iri" : "https://example.org/partidos/tieneJornada",
    "baseIri" : "https://example.org/partidos",
    "range" : "15",
    "label" : {
      "IRI-based" : "tieneJornada",
      "undefined" : "tiene jornada"
    },
    "domain" : "1",
    "comment" : {
      "undefined" : "Relaciona un grupo con sus jornadas."
    },
    "attributes" : [ "object" ],
    "id" : "37"
  }, {
    "iri" : "https://example.org/partidos/sameAsDeporte",
    "baseIri" : "https://example.org/partidos",
    "range" : "29",
    "label" : {
      "IRI-based" : "sameAsDeporte",
      "undefined" : "same as deporte"
    },
    "domain" : "12",
    "comment" : {
      "undefined" : "URI externa equivalente para el deporte (enlace a recurso LOD)."
    },
    "attributes" : [ "datatype" ],
    "id" : "39"
  }, {
    "iri" : "https://example.org/partidos/ocurreEn",
    "baseIri" : "https://example.org/partidos",
    "range" : "4",
    "label" : {
      "IRI-based" : "ocurreEn",
      "undefined" : "ocurre en"
    },
    "domain" : "16",
    "comment" : {
      "undefined" : "Campo donde se celebra el partido."
    },
    "attributes" : [ "object" ],
    "id" : "40"
  }, {
    "iri" : "https://example.org/partidos/tieneGrupo",
    "baseIri" : "https://example.org/partidos",
    "range" : "1",
    "label" : {
      "IRI-based" : "tieneGrupo",
      "undefined" : "tiene grupo"
    },
    "domain" : "7",
    "comment" : {
      "undefined" : "Relaciona una competición con sus grupos."
    },
    "attributes" : [ "object" ],
    "id" : "43"
  }, {
    "iri" : "https://example.org/partidos/tipoDe",
    "baseIri" : "https://example.org/partidos",
    "range" : "12",
    "label" : {
      "IRI-based" : "tipoDe",
      "undefined" : "tipo de"
    },
    "domain" : "7",
    "comment" : {
      "undefined" : "Relaciona una competición con el deporte al que pertenece."
    },
    "attributes" : [ "object" ],
    "id" : "46"
  }, {
    "iri" : "https://example.org/partidos/coorY",
    "baseIri" : "https://example.org/partidos",
    "range" : "44",
    "label" : {
      "IRI-based" : "coorY",
      "undefined" : "coordenada Y"
    },
    "domain" : "4",
    "comment" : {
      "undefined" : "Coordenada Y (latitud) de la ubicación del campo."
    },
    "attributes" : [ "datatype" ],
    "id" : "47"
  }, {
    "iri" : "https://example.org/partidos/coorX",
    "baseIri" : "https://example.org/partidos",
    "range" : "42",
    "label" : {
      "IRI-based" : "coorX",
      "undefined" : "coordenada X"
    },
    "domain" : "4",
    "comment" : {
      "undefined" : "Coordenada X (longitud) de la ubicación del campo."
    },
    "attributes" : [ "datatype" ],
    "id" : "48"
  }, {
    "iri" : "https://example.org/partidos/categoria",
    "baseIri" : "https://example.org/partidos",
    "range" : "49",
    "label" : {
      "IRI-based" : "categoria",
      "undefined" : "categoria"
    },
    "domain" : "1",
    "comment" : {
      "undefined" : "Categoría de edad o nivel del grupo."
    },
    "attributes" : [ "datatype" ],
    "id" : "51"
  }, {
    "iri" : "https://example.org/partidos/sameAsDistrito",
    "baseIri" : "https://example.org/partidos",
    "range" : "31",
    "label" : {
      "IRI-based" : "sameAsDistrito",
      "undefined" : "same as distrito"
    },
    "domain" : "22",
    "comment" : {
      "undefined" : "URI externa equivalente para el distrito (enlace a recurso LOD)."
    },
    "attributes" : [ "datatype" ],
    "id" : "52"
  }, {
    "iri" : "https://example.org/partidos/programado",
    "baseIri" : "https://example.org/partidos",
    "range" : "36",
    "label" : {
      "IRI-based" : "programado",
      "undefined" : "programado"
    },
    "domain" : "16",
    "comment" : {
      "undefined" : "Indica si el partido está programado (true) o no (false)."
    },
    "attributes" : [ "datatype" ],
    "id" : "53"
  }, {
    "iri" : "https://example.org/partidos/resultado2",
    "baseIri" : "https://example.org/partidos",
    "range" : "30",
    "label" : {
      "IRI-based" : "resultado2",
      "undefined" : "resultado2"
    },
    "domain" : "16",
    "comment" : {
      "undefined" : "Goles o puntos del equipo visitante."
    },
    "attributes" : [ "datatype" ],
    "id" : "54"
  }, {
    "iri" : "https://example.org/partidos/resultado1",
    "baseIri" : "https://example.org/partidos",
    "range" : "35",
    "label" : {
      "IRI-based" : "resultado1",
      "undefined" : "resultado1"
    },
    "domain" : "16",
    "comment" : {
      "undefined" : "Goles o puntos del equipo local."
    },
    "attributes" : [ "datatype" ],
    "id" : "55"
  }, {
    "iri" : "https://example.org/partidos/nombreDistrito",
    "baseIri" : "https://example.org/partidos",
    "range" : "38",
    "label" : {
      "IRI-based" : "nombreDistrito",
      "undefined" : "nombre distrito"
    },
    "domain" : "22",
    "comment" : {
      "undefined" : "Nombre del distrito."
    },
    "attributes" : [ "datatype" ],
    "id" : "56"
  }, {
    "iri" : "https://example.org/partidos/codigoCampo",
    "baseIri" : "https://example.org/partidos",
    "range" : "50",
    "label" : {
      "IRI-based" : "codigoCampo",
      "undefined" : "codigo campo"
    },
    "domain" : "4",
    "comment" : {
      "undefined" : "Código numérico identificador del campo."
    },
    "attributes" : [ "datatype" ],
    "id" : "57"
  }, {
    "iri" : "https://example.org/partidos/localizadoEn",
    "baseIri" : "https://example.org/partidos",
    "range" : "22",
    "label" : {
      "IRI-based" : "localizadoEn",
      "undefined" : "localizado en"
    },
    "domain" : "4",
    "comment" : {
      "undefined" : "Distrito donde está ubicado el campo."
    },
    "attributes" : [ "object" ],
    "id" : "58"
  }, {
    "iri" : "https://example.org/partidos/nombreEquipo",
    "baseIri" : "https://example.org/partidos",
    "range" : "34",
    "label" : {
      "IRI-based" : "nombreEquipo",
      "undefined" : "nombre equipo"
    },
    "domain" : "19",
    "comment" : {
      "undefined" : "Nombre del equipo."
    },
    "attributes" : [ "datatype" ],
    "id" : "59"
  }, {
    "iri" : "https://example.org/partidos/hora",
    "baseIri" : "https://example.org/partidos",
    "range" : "45",
    "label" : {
      "IRI-based" : "hora",
      "undefined" : "hora"
    },
    "domain" : "16",
    "comment" : {
      "undefined" : "Hora de inicio del partido."
    },
    "attributes" : [ "datatype" ],
    "id" : "60"
  }, {
    "iri" : "https://example.org/partidos/codigoJornada",
    "baseIri" : "https://example.org/partidos",
    "range" : "41",
    "label" : {
      "IRI-based" : "codigoJornada",
      "undefined" : "codigo jornada"
    },
    "domain" : "15",
    "comment" : {
      "undefined" : "Código numérico identificador de la jornada."
    },
    "attributes" : [ "datatype" ],
    "id" : "61"
  } ]
}